rateToolsAC4RM/__init__.py
rateToolsAC4RM/rateTools.py
rateToolsAC4RM-0.45.dist-info/METADATA
rateToolsAC4RM-0.45.dist-info/WHEEL
rateToolsAC4RM-0.45.dist-info/top_level.txt
rateToolsAC4RM-0.45.dist-info/RECORD
