Metadata-Version: 2.1
Name: rateToolsAC4RM
Version: 0.45
Summary: rate tools for fwd deltas
Home-page: UNKNOWN
Author-email: tl2034@columbia.edu
License: UNKNOWN
Platform: UNKNOWN
